Workbook

Sheet README
A1: Loop Engineering workbook
A2: From the guide 'Loop Engineering: From Zero to Hero' (docs/loop-engineering). Every result is a live formula.
A4: How to use | B4: Type only in yellow cells. Blue cells are formulas; don't type over them. Orange cells are FIELD WORK: look the value up before you trust the result.
A5: Color key | B5: Yellow = input · Blue = formula · Orange = FIELD WORK (current prices, your own measurements)
A6: CALC-1 Verifier Trust | B6: When the checker says 'pass', how often is the work really right? (Level 2)
A7: CALC-2 Tries | B7: How many tries should the cap allow? Includes a table of n = 1 to 20. (Level 3)
A8: CALC-3 Budget | B8: Cost per iteration, typical run, ceiling per run, monthly ceiling, time ceiling. (Level 4)
A9: CALC-4 Scorecard | B9: The Loop Scorecard /100, with CS-1 v1, CS-1 v2, and the kit's loop.sh default pre-filled. (Level 5)
A10: Loop Canvas | B10: The nine-box Loop Spec as a fill-in sheet, matching kit/LOOP-SPEC.md. (Level 1)
A11: Run Log | B11: One row per iteration, same columns as kit/loop.sh writes; cost per row and summary numbers. (Level 5)
A12: ⚠VERIFY: prices | B12: The 'Example' column of CALC-3 uses INVENTED round prices ($4 and $20 per million tokens) so the arithmetic is easy to check. They are not real prices. Put current prices from Anthropic's pricing page in the 'Yours' column.
A13: Checksums | B13: Each calculator sheet has a 'Checksum' table: the guide's worked examples, the workbook's result, and a match column. If a match cell says NO, a formula has been changed.
A14: No macros, no links | B14: This workbook has no macros and no links to other files.

Sheet CALC-1 Verifier Trust
A1: CALC-1 · VERIFIER TRUST
A2: When the checker says 'pass', how often is the work really right?
A4: Input | B4: Symbol | C4: Your value
A5: Share of attempts correct before any check | B5: p | C5: 0.3
A6: Chance the checker passes correct work | B6: S | C6: 0.9
A7: Chance the checker passes wrong work (false-pass rate) | B7: F | C7: 0.2
A9: Result | C9: Value
A10: Trust = p×S ÷ (p×S + (1 − p)×F) | C10: =C5*C6/(C5*C6+(1-C5)*C7)
A11: Share of passes that are wrong = 1 − Trust | C11: =1-C10
A12: Band | C12: =IF(C10>=0.95,"95%+: unattended, with spot checks",IF(C10>=0.8,"80-94%: a human checks a sample","under 80%: don't run unattended"))
A14: Assumptions (adjustable): p, S, F stay about the same between runs; a 10 + 10 sample is only a rough estimate; checker mistakes that cluster on hard cases make true trust lower.
A16: Checksum case (from the guide) | B16: p | C16: S | D16: F | E16: Trust (formula) | F16: Expected | G16: Match
A17: Loose checker | B17: 0.3 | C17: 0.9 | D17: 0.2 | E17: =B17*C17/(B17*C17+(1-B17)*D17) | F17: 0.659 | G17: =IF(ABS(E17-F17)<0.0005,"yes","NO")
A18: Tight checker | B18: 0.3 | C18: 0.9 | D18: 0.02 | E18: =B18*C18/(B18*C18+(1-B18)*D18) | F18: 0.951 | G18: =IF(ABS(E18-F18)<0.0005,"yes","NO")
A19: Better prompt, loose checker | B19: 0.5 | C19: 0.9 | D19: 0.2 | E19: =B19*C19/(B19*C19+(1-B19)*D19) | F19: 0.818 | G19: =IF(ABS(E19-F19)<0.0005,"yes","NO")

Sheet CALC-2 Tries
A1: CALC-2 · TRIES-TO-SUCCESS
A2: How many tries should the cap allow?
A4: Input | B4: Symbol | C4: Your value
A5: Chance a single try succeeds (above 0, below 1) | B5: p | C5: 0.5
A6: Confidence you want (above 0, below 1) | B6: C | C6: 0.95
A7: A cap to test | B7: n | C7: 5
A9: Result | C9: Value
A10: Tries needed = round up ln(1 − C) ÷ ln(1 − p) | C10: =ROUNDUP(LN(1-C6)/LN(1-C5)-1E-9,0)
A11: Chance of success within the tries needed | C11: =1-(1-C5)^C10
A12: Chance of success within the cap n | C12: =1-(1-C5)^C7
A13: Average tries to the first success = 1 ÷ p | C13: =1/C5
A14: Average tries actually used with cap n = (1 − (1 − p)^n) ÷ p | C14: =(1-(1-C5)^C7)/C5
A15: Band | C15: =IF(C10<=5,"5 or fewer: comfortable",IF(C10<=15,"6-15: set a budget ceiling too (CALC-3)","over 15: better checker or smaller steps"))
A17: Assumptions (adjustable): tries are independent with the same p. Good feedback often beats this; a weak checker or a filling context can do worse. The -1E-9 guards against rounding error when the ratio is a whole number.
A19: Checksum case (from the guide) | B19: p | C19: C | D19: Tries (formula) | E19: Chance within tries | F19: Expected tries | G19: Match
A20: p = 0.5, C = 0.95 | B20: 0.5 | C20: 0.95 | D20: =ROUNDUP(LN(1-C20)/LN(1-B20)-1E-9,0) | E20: =1-(1-B20)^D20 | F20: 5 | G20: =IF(AND(D20=F20,ABS(E20-0.969)<0.0005),"yes","NO")
A21: p = 0.2, C = 0.90 | B21: 0.2 | C21: 0.9 | D21: =ROUNDUP(LN(1-C21)/LN(1-B21)-1E-9,0) | E21: =1-(1-B21)^D21 | F21: 11 | G21: =IF(AND(D21=F21,ABS(E21-0.914)<0.0005),"yes","NO")
A22: p = 0.4, C = 0.90 (Level 3 practice) | B22: 0.4 | C22: 0.9 | D22: =ROUNDUP(LN(1-C22)/LN(1-B22)-1E-9,0) | E22: =1-(1-B22)^D22 | F22: 5 | G22: =IF(AND(D22=F22,ABS(E22-0.922)<0.0005),"yes","NO")
A24: Tries n | B24: p = 0.2 | C24: p = 0.5 | D24: p = 0.8
A25: p values → | B25: 0.2 | C25: 0.5 | D25: 0.8
A26: 1 | B26: =1-(1-B$25)^$A26 | C26: =1-(1-C$25)^$A26 | D26: =1-(1-D$25)^$A26
A27: 2 | B27: =1-(1-B$25)^$A27 | C27: =1-(1-C$25)^$A27 | D27: =1-(1-D$25)^$A27
A28: 3 | B28: =1-(1-B$25)^$A28 | C28: =1-(1-C$25)^$A28 | D28: =1-(1-D$25)^$A28
A29: 4 | B29: =1-(1-B$25)^$A29 | C29: =1-(1-C$25)^$A29 | D29: =1-(1-D$25)^$A29
A30: 5 | B30: =1-(1-B$25)^$A30 | C30: =1-(1-C$25)^$A30 | D30: =1-(1-D$25)^$A30
A31: 6 | B31: =1-(1-B$25)^$A31 | C31: =1-(1-C$25)^$A31 | D31: =1-(1-D$25)^$A31
A32: 7 | B32: =1-(1-B$25)^$A32 | C32: =1-(1-C$25)^$A32 | D32: =1-(1-D$25)^$A32
A33: 8 | B33: =1-(1-B$25)^$A33 | C33: =1-(1-C$25)^$A33 | D33: =1-(1-D$25)^$A33
A34: 9 | B34: =1-(1-B$25)^$A34 | C34: =1-(1-C$25)^$A34 | D34: =1-(1-D$25)^$A34
A35: 10 | B35: =1-(1-B$25)^$A35 | C35: =1-(1-C$25)^$A35 | D35: =1-(1-D$25)^$A35
A36: 11 | B36: =1-(1-B$25)^$A36 | C36: =1-(1-C$25)^$A36 | D36: =1-(1-D$25)^$A36
A37: 12 | B37: =1-(1-B$25)^$A37 | C37: =1-(1-C$25)^$A37 | D37: =1-(1-D$25)^$A37
... A45: 20 | B45: =1-(1-B$25)^$A45 | C45: =1-(1-C$25)^$A45 | D45: =1-(1-D$25)^$A45

Sheet CALC-3 Budget
A1: CALC-3 · LOOP BUDGET
A2: What can one run, and a month of runs, cost in money and time?
A4: Input | B4: Symbol | C4: Example (INVENTED prices) | D4: Yours
A5: Input tokens per iteration | B5: Tin | C5: 20000
A6: Output tokens per iteration | B6: Tout | C6: 2000
A7: Price per million input tokens ($) ⚠VERIFY | B7: Pin | C7: 4
A8: Price per million output tokens ($) ⚠VERIFY | B8: Pout | C8: 20
A9: Chance one iteration succeeds (from CALC-2) | B9: p | C9: 0.5
A10: Iteration cap (from CALC-2) | B10: N | C10: 5
A11: Minutes per iteration | B11: M | C11: 3
A12: Runs per month | B12: R | C12: 30
A14: Result | C14: Example | D14: Yours
A15: Cost per iteration = (Tin×Pin + Tout×Pout) ÷ 1,000,000 | C15: =(C5*C7+C6*C8)/1000000 | D15: =IF(COUNT(D5:D8)=4,(D5*D7+D6*D8)/1000000,"")
A16: Typical run ≈ (1 ÷ p) × cost per iteration | C16: =(1/C9)*C15 | D16: =IF(AND(ISNUMBER(D9),ISNUMBER(D15)),(1/D9)*D15,"")
A17: Ceiling per run = N × cost per iteration | C17: =C10*C15 | D17: =IF(AND(ISNUMBER(D10),ISNUMBER(D15)),D10*D15,"")
A18: Monthly ceiling = R × ceiling per run | C18: =C12*C17 | D18: =IF(AND(ISNUMBER(D12),ISNUMBER(D17)),D12*D17,"")
A19: Time ceiling per run (minutes) = N × M | C19: =C10*C11 | D19: =IF(COUNT(D10:D11)=2,D10*D11,"")
A21: The 'Example' prices are INVENTED round numbers for easy arithmetic, not real prices. Put current prices from Anthropic's pricing page in the orange 'Yours' cells (FIELD WORK). Prompt caching and subscription plans change the picture: check the current pricing and plan pages.
A23: Checksum (Example column) | C23: Workbook | D23: Expected | E23: Match
A24: Cost per iteration | C24: =C15 | D24: 0.12 | E24: =IF(ABS(C24-D24)<0.0005,"yes","NO")
A25: Typical run | C25: =C16 | D25: 0.24 | E25: =IF(ABS(C25-D25)<0.0005,"yes","NO")
A26: Ceiling per run | C26: =C17 | D26: 0.6 | E26: =IF(ABS(C26-D26)<0.0005,"yes","NO")
A27: Monthly ceiling | C27: =C18 | D27: 18 | E27: =IF(ABS(C27-D27)<0.0005,"yes","NO")
A28: Time ceiling (min) | C28: =C19 | D28: 15 | E28: =IF(ABS(C28-D28)<0.0005,"yes","NO")

Sheet CALC-4 Scorecard
A1: CALC-4 · LOOP SCORECARD /100
A2: Rate each criterion 0-5. Score = 3 × (criteria 1-4) + 2 × (criteria 5-8).
A4: Criterion | B4: Weight | C4: CS-1 v1 | D4: CS-1 v2 | E4: kit loop.sh default | F4: Yours | G4: What a 5 looks like
A5: 1 Goal & done condition | B5: 3 | C5: 2 | D5: 5 | E5: 2 | G5: An end state a machine can check, with a success exit and a failure exit
A6: 2 Checker | B6: 3 | C6: 1 | D6: 5 | E6: 2 | G6: Separate from the maker, 'not yet' by default, trust estimated with CALC-1
A7: 3 Stop rules & budget | B7: 3 | C7: 0 | D7: 5 | E7: 4 | G7: Caps on iterations, spend, and time; a STUCK rule; the ceiling known from CALC-2 and CALC-3
A8: 4 Safety | B8: 3 | C8: 1 | D8: 4 | E8: 4 | G8: Isolated workspace, least permissions, no destructive defaults, secrets out, injection considered, a kill switch
A9: 5 State & memory | B9: 2 | C9: 1 | D9: 4 | E9: 3 | G9: Kept in files outside the model; a fresh session can resume from them
A10: 6 Observability | B10: 2 | C10: 1 | D10: 4 | E10: 3 | G10: A run log for every iteration and the five numbers from Level 5
A11: 7 Human touchpoints | B11: 2 | C11: 1 | D11: 4 | E11: 3 | G11: An escalation package, approval where the stakes need it, the autonomy rung stated
A12: 8 Reusability | B12: 2 | C12: 1 | D12: 4 | E12: 4 | G12: A one-page Loop Spec, a version number, placeholders, easy to adapt
A13: Score /100 | C13: =IF(COUNT(C5:C12)=8,3*SUM(C5:C8)+2*SUM(C9:C12),"") | D13: =IF(COUNT(D5:D12)=8,3*SUM(D5:D8)+2*SUM(D9:D12),"") | E13: =IF(COUNT(E5:E12)=8,3*SUM(E5:E8)+2*SUM(E9:E12),"") | F13: =IF(COUNT(F5:F12)=8,3*SUM(F5:F8)+2*SUM(F9:F12),"")
A14: Band | C14: =IF(C13="","",IF(C13>=90,"hero-grade",IF(C13>=75,"strong",IF(C13>=60,"working","draft")))) | D14: =IF(D13="","",IF(D13>=90,"hero-grade",IF(D13>=75,"strong",IF(D13>=60,"working","draft")))) | E14: =IF(E13="","",IF(E13>=90,"hero-grade",IF(E13>=75,"strong",IF(E13>=60,"working","draft")))) | F14: =IF(F13="","",IF(F13>=90,"hero-grade",IF(F13>=75,"strong",IF(F13>=60,"working","draft"))))
A16: Bands: 0-59 draft (don't run unattended) · 60-74 working (run it while you watch) · 75-89 strong (unattended, with caps and spot checks) · 90-100 hero-grade. Every rating below 4 names the fix that would raise it.
A18: Checksum | C18: Workbook | D18: Expected | E18: Match
A19: CS-1 v1 | C19: =C13 | D19: 20 | E19: =IF(C19=D19,"yes","NO")
A20: CS-1 v2 | C20: =D13 | D20: 89 | E20: =IF(C20=D20,"yes","NO")
A21: kit loop.sh default | C21: =E13 | D21: 62 | E21: =IF(C21=D21,"yes","NO")

Sheet Loop Canvas
A1: LOOP CANVAS · the nine-box Loop Spec
A2: Matches kit/LOOP-SPEC.md. Fill in the yellow cells; start from DONE WHEN (TIP-1.1).
A4: Header | B4: Question | C4: Your answer
A5: NAME | B5: What do you call this loop?
A6: VERSION | B6: v0.1, then bump on every change
A7: OWNER | B7: Which person owns it? (not 'the team')
A8: AUTONOMY RUNG | B8: 1 watch · 2 suggest · 3 act with approval · 4 act alone
A9: RISK LEVEL | B9: What a bad run costs: low · medium · high
A11: Box | B11: Question | C11: Your answer
A12: 1 GOAL | B12: What end state are we after, in one sentence?
A13: 2 DONE WHEN | B13: How can a machine tell the goal is reached? (the success exit)
A14: 3 TRIGGER | B14: What starts a run: you, a schedule, an event, or a goal?
A15: 4 ACTOR | B15: Which agent and model, with which tools allowed?
A16: 5 CONTEXT | B16: What does each run read first?
A17: 6 CHECKER | B17: Who checks, how, and with what default? (not yet)
A18: 7 STATE | B18: What gets written down between runs, and where?
A19: 8 LIMITS | B19: DONE · CAP · STUCK · DANGER · HUMAN: one rule each
A20: 9 ESCALATION | B20: Who gets called, with what evidence?
A22: Changelog | B22: Date | C22: What changed, and why

Sheet Run Log
A1: RUN LOG · one row per iteration (same columns as kit/loop.sh)
A3: iteration | B3: started_at | C3: action | D3: check_result | E3: stop_reason | F3: tokens_in | G3: tokens_out | H3: diff_lines | I3: note | J3: cost ($) | L3: SUMMARY (rows 4-503)
A4: 1 | B4: 2026-09-20T02:00:04Z | C4: agent | D4: fail | F4: 21044 | G4: 1893 | H4: 14 | I4: FAIL: test_refund_rounding expected 10.01, got 10.00 | J4: =IF(AND(ISNUMBER(F4),ISNUMBER(G4)),(F4*IF(ISNUMBER('CALC-3 Budget'!$D$7),'CALC-3 Budget'!$D$7,'CALC-3 Budget'!$C$7)+G4*IF(ISNUMBER('CALC-3 Budget'!$D$8),'CALC-3 Budget'!$D$8,'CALC-3 Budget'!$C$8))/1000000,"") | L4: Runs (rows with a stop_reason) | M4: =COUNTA(E4:E503)
A5: 2 | B5: 2026-09-20T02:03:11Z | C5: agent | D5: fail | F5: 22318 | G5: 2210 | H5: 9 | I5: FAIL: test_tax_totals expected 3.15, got 3.14 | J5: =IF(AND(ISNUMBER(F5),ISNUMBER(G5)),(F5*IF(ISNUMBER('CALC-3 Budget'!$D$7),'CALC-3 Budget'!$D$7,'CALC-3 Budget'!$C$7)+G5*IF(ISNUMBER('CALC-3 Budget'!$D$8),'CALC-3 Budget'!$D$8,'CALC-3 Budget'!$C$8))/1000000,"") | L5: Successful runs (DONE) | M5: =COUNTIF(E4:E503,"DONE")
A6: 3 | B6: 2026-09-20T02:06:40Z | C6: agent | D6: pass | E6: DONE | F6: 22901 | G6: 1650 | H6: 6 | I6: 12 passed, 0 failed | J6: =IF(AND(ISNUMBER(F6),ISNUMBER(G6)),(F6*IF(ISNUMBER('CALC-3 Budget'!$D$7),'CALC-3 Budget'!$D$7,'CALC-3 Budget'!$C$7)+G6*IF(ISNUMBER('CALC-3 Budget'!$D$8),'CALC-3 Budget'!$D$8,'CALC-3 Budget'!$C$8))/1000000,"") | L6: Iterations used (not skipped) | M6: =COUNTIFS(A4:A503,">0",D4:D503,"<>skipped")
J7: =IF(AND(ISNUMBER(F7),ISNUMBER(G7)),(F7*IF(ISNUMBER('CALC-3 Budget'!$D$7),'CALC-3 Budget'!$D$7,'CALC-3 Budget'!$C$7)+G7*IF(ISNUMBER('CALC-3 Budget'!$D$8),'CALC-3 Budget'!$D$8,'CALC-3 Budget'!$C$8))/1000000,"") | L7: Success rate | M7: =IF(M4>0,M5/M4,"")
J8: =IF(AND(ISNUMBER(F8),ISNUMBER(G8)),(F8*IF(ISNUMBER('CALC-3 Budget'!$D$7),'CALC-3 Budget'!$D$7,'CALC-3 Budget'!$C$7)+G8*IF(ISNUMBER('CALC-3 Budget'!$D$8),'CALC-3 Budget'!$D$8,'CALC-3 Budget'!$C$8))/1000000,"") | L8: Iterations per success | M8: =IF(M5>0,M6/M5,"")
J9: =IF(AND(ISNUMBER(F9),ISNUMBER(G9)),(F9*IF(ISNUMBER('CALC-3 Budget'!$D$7),'CALC-3 Budget'!$D$7,'CALC-3 Budget'!$C$7)+G9*IF(ISNUMBER('CALC-3 Budget'!$D$8),'CALC-3 Budget'!$D$8,'CALC-3 Budget'!$C$8))/1000000,"") | L9: Total cost ($) | M9: =SUM(J4:J503)
J10: =IF(AND(ISNUMBER(F10),ISNUMBER(G10)),(F10*IF(ISNUMBER('CALC-3 Budget'!$D$7),'CALC-3 Budget'!$D$7,'CALC-3 Budget'!$C$7)+G10*IF(ISNUMBER('CALC-3 Budget'!$D$8),'CALC-3 Budget'!$D$8,'CALC-3 Budget'!$C$8))/1000000,"") | L10: Cost per success ($) | M10: =IF(M5>0,M9/M5,"")
J11: =IF(AND(ISNUMBER(F11),ISNUMBER(G11)),(F11*IF(ISNUMBER('CALC-3 Budget'!$D$7),'CALC-3 Budget'!$D$7,'CALC-3 Budget'!$C$7)+G11*IF(ISNUMBER('CALC-3 Budget'!$D$8),'CALC-3 Budget'!$D$8,'CALC-3 Budget'!$C$8))/1000000,"") | L11: Prices in use | M11: =IF(AND(ISNUMBER('CALC-3 Budget'!D7),ISNUMBER('CALC-3 Budget'!D8)),"yours","INVENTED example prices")
J12: =IF(AND(ISNUMBER(F12),ISNUMBER(G12)),(F12*IF(ISNUMBER('CALC-3 Budget'!$D$7),'CALC-3 Budget'!$D$7,'CALC-3 Budget'!$C$7)+G12*IF(ISNUMBER('CALC-3 Budget'!$D$8),'CALC-3 Budget'!$D$8,'CALC-3 Budget'!$C$8))/1000000,"")
J13: =IF(AND(ISNUMBER(F13),ISNUMBER(G13)),(F13*IF(ISNUMBER('CALC-3 Budget'!$D$7),'CALC-3 Budget'!$D$7,'CALC-3 Budget'!$C$7)+G13*IF(ISNUMBER('CALC-3 Budget'!$D$8),'CALC-3 Budget'!$D$8,'CALC-3 Budget'!$C$8))/1000000,"") | L13: Rows 4-6 are the example from Level 5 (EX-5.1). Delete them and paste your own loop-log.csv rows. Cost uses your CALC-3 prices when filled, otherwise the invented example prices.
J14: =IF(AND(ISNUMBER(F14),ISNUMBER(G14)),(F14*IF(ISNUMBER('CALC-3 Budget'!$D$7),'CALC-3 Budget'!$D$7,'CALC-3 Budget'!$C$7)+G14*IF(ISNUMBER('CALC-3 Budget'!$D$8),'CALC-3 Budget'!$D$8,'CALC-3 Budget'!$C$8))/1000000,"")
J15: =IF(AND(ISNUMBER(F15),ISNUMBER(G15)),(F15*IF(ISNUMBER('CALC-3 Budget'!$D$7),'CALC-3 Budget'!$D$7,'CALC-3 Budget'!$C$7)+G15*IF(ISNUMBER('CALC-3 Budget'!$D$8),'CALC-3 Budget'!$D$8,'CALC-3 Budget'!$C$8))/1000000,"")
J16: =IF(AND(ISNUMBER(F16),ISNUMBER(G16)),(F16*IF(ISNUMBER('CALC-3 Budget'!$D$7),'CALC-3 Budget'!$D$7,'CALC-3 Budget'!$C$7)+G16*IF(ISNUMBER('CALC-3 Budget'!$D$8),'CALC-3 Budget'!$D$8,'CALC-3 Budget'!$C$8))/1000000,"")
J17: =IF(AND(ISNUMBER(F17),ISNUMBER(G17)),(F17*IF(ISNUMBER('CALC-3 Budget'!$D$7),'CALC-3 Budget'!$D$7,'CALC-3 Budget'!$C$7)+G17*IF(ISNUMBER('CALC-3 Budget'!$D$8),'CALC-3 Budget'!$D$8,'CALC-3 Budget'!$C$8))/1000000,"")
J18: =IF(AND(ISNUMBER(F18),ISNUMBER(G18)),(F18*IF(ISNUMBER('CALC-3 Budget'!$D$7),'CALC-3 Budget'!$D$7,'CALC-3 Budget'!$C$7)+G18*IF(ISNUMBER('CALC-3 Budget'!$D$8),'CALC-3 Budget'!$D$8,'CALC-3 Budget'!$C$8))/1000000,"")
J19: =IF(AND(ISNUMBER(F19),ISNUMBER(G19)),(F19*IF(ISNUMBER('CALC-3 Budget'!$D$7),'CALC-3 Budget'!$D$7,'CALC-3 Budget'!$C$7)+G19*IF(ISNUMBER('CALC-3 Budget'!$D$8),'CALC-3 Budget'!$D$8,'CALC-3 Budget'!$C$8))/1000000,"")
J20: =IF(AND(ISNUMBER(F20),ISNUMBER(G20)),(F20*IF(ISNUMBER('CALC-3 Budget'!$D$7),'CALC-3 Budget'!$D$7,'CALC-3 Budget'!$C$7)+G20*IF(ISNUMBER('CALC-3 Budget'!$D$8),'CALC-3 Budget'!$D$8,'CALC-3 Budget'!$C$8))/1000000,"")
J21: =IF(AND(ISNUMBER(F21),ISNUMBER(G21)),(F21*IF(ISNUMBER('CALC-3 Budget'!$D$7),'CALC-3 Budget'!$D$7,'CALC-3 Budget'!$C$7)+G21*IF(ISNUMBER('CALC-3 Budget'!$D$8),'CALC-3 Budget'!$D$8,'CALC-3 Budget'!$C$8))/1000000,"")
J22: =IF(AND(ISNUMBER(F22),ISNUMBER(G22)),(F22*IF(ISNUMBER('CALC-3 Budget'!$D$7),'CALC-3 Budget'!$D$7,'CALC-3 Budget'!$C$7)+G22*IF(ISNUMBER('CALC-3 Budget'!$D$8),'CALC-3 Budget'!$D$8,'CALC-3 Budget'!$C$8))/1000000,"")
J23: =IF(AND(ISNUMBER(F23),ISNUMBER(G23)),(F23*IF(ISNUMBER('CALC-3 Budget'!$D$7),'CALC-3 Budget'!$D$7,'CALC-3 Budget'!$C$7)+G23*IF(ISNUMBER('CALC-3 Budget'!$D$8),'CALC-3 Budget'!$D$8,'CALC-3 Budget'!$C$8))/1000000,"")
J24: =IF(AND(ISNUMBER(F24),ISNUMBER(G24)),(F24*IF(ISNUMBER('CALC-3 Budget'!$D$7),'CALC-3 Budget'!$D$7,'CALC-3 Budget'!$C$7)+G24*IF(ISNUMBER('CALC-3 Budget'!$D$8),'CALC-3 Budget'!$D$8,'CALC-3 Budget'!$C$8))/1000000,"")
J25: =IF(AND(ISNUMBER(F25),ISNUMBER(G25)),(F25*IF(ISNUMBER('CALC-3 Budget'!$D$7),'CALC-3 Budget'!$D$7,'CALC-3 Budget'!$C$7)+G25*IF(ISNUMBER('CALC-3 Budget'!$D$8),'CALC-3 Budget'!$D$8,'CALC-3 Budget'!$C$8))/1000000,"")
... J503: =IF(AND(ISNUMBER(F503),ISNUMBER(G503)),(F503*IF(ISNUMBER('CALC-3 Budget'!$D$7),'CALC-3 Budget'!$D$7,'CALC-3 Budget'!$C$7)+G503*IF(ISNUMBER('CALC-3 Budget'!$D$8),'CALC-3 Budget'!$D$8,'CALC-3 Budget'!$C$8))/1000000,"")
